{
    "Name": "Teleport",
    "Type": "Psychic",
    "Power": 0,
    "Damage1": "",
    "Damage2": "",
    "Accuracy1": "Special",
    "Accuracy2": "Channel",
    "Target": "Self",
    "Effect": "Target Self. Switcher Move for the User. Out of battle, Teleportatin distances and limitations are determined by the User's Special Score and Storyteller's discretion.",
    "Description": "Teleport the user and one more creature to a place of tranquility and high psychic resonance such as Pokémon Centers. Ceilings and walls block this move from working.",
    "_id": "teleport",
    "Attributes": {
        "SwitcherMove": "User"
    },
    "AddedEffects": {},
    "Category": "Support"
}