{
    "Name": "Rapid Spin",
    "Type": "Normal",
    "Power": 2,
    "Damage1": "Strength",
    "Damage2": "",
    "Accuracy1": "Dexterity",
    "Accuracy2": "Brawl",
    "Target": "Foe",
    "Effect": "Remove Entry Hazards (Spikes, Stealth Rock, etc.) and Leech Seed from the user's side of the field. Increase user's Dexterity.",
    "Description": "The Pokemon spins swiftly to strike the foe. Anything near will be scattered around.",
    "_id": "rapid-spin",
    "Attributes": {},
    "AddedEffects": {
        "StatChanges": [
            {
                "Stats": [
                    "Dexterity"
                ],
                "Stages": 1,
                "Affects": "User"
            }
        ]
    },
    "Category": "Physical"
}