{
    "Name": "Sonic Boom",
    "Type": "Normal",
    "Power": 0,
    "Damage1": "",
    "Damage2": "",
    "Accuracy1": "Special",
    "Accuracy2": "Stealth",
    "Target": "Foe",
    "Effect": "Single Target. This Moves always inflicts 1 damage. Ignore Defenses, Force Fields, Shield Moves, Type Resistance and Abilities that would prevent this damage.",
    "Description": "The Pokémon attacks with a small destructive shock that can go through armor, thick hide, or walls to deal some damage.",
    "_id": "sonic-boom",
    "Attributes": {
        "IgnoreDefenses": true,
        "IgnoreShield": true
    },
    "AddedEffects": {},
    "Category": "Special"
}
