{
    "Name": "Cleffa",
    "_id": "cleffa",
    "Moves": [
        {
            "Learned": "Starter",
            "Name": "Pound"
        },
        {
            "Learned": "Starter",
            "Name": "Charm"
        },
        {
            "Learned": "Beginner",
            "Name": "Encore"
        },
        {
            "Learned": "Beginner",
            "Name": "Sweet Kiss"
        },
        {
            "Learned": "Amateur",
            "Name": "Sing"
        },
        {
            "Learned": "Amateur",
            "Name": "Copycat"
        },
        {
            "Learned": "Amateur",
            "Name": "Tickle"
        },
        {
            "Learned": "Amateur",
            "Name": "Fake Tears"
        },
        {
            "Learned": "Ace",
            "Name": "Magical Leaf"
        },
        {
            "Learned": "Pro",
            "Name": "Wonder Room"
        }
    ]
}