{
    "Name": "Mareep",
    "_id": "mareep",
    "Moves": [
        {
            "Learned": "Starter",
            "Name": "Tackle"
        },
        {
            "Learned": "Starter",
            "Name": "Growl"
        },
        {
            "Learned": "Beginner",
            "Name": "Thunder Wave"
        },
        {
            "Learned": "Beginner",
            "Name": "Thunder Shock"
        },
        {
            "Learned": "Amateur",
            "Name": "Cotton Spore"
        },
        {
            "Learned": "Amateur",
            "Name": "Charge"
        },
        {
            "Learned": "Amateur",
            "Name": "Take Down"
        },
        {
            "Learned": "Amateur",
            "Name": "Electro Ball"
        },
        {
            "Learned": "Amateur",
            "Name": "Confuse Ray"
        },
        {
            "Learned": "Amateur",
            "Name": "Power Gem"
        },
        {
            "Learned": "Amateur",
            "Name": "Signal Beam"
        },
        {
            "Learned": "Ace",
            "Name": "Cotton Guard"
        },
        {
            "Learned": "Ace",
            "Name": "Discharge"
        },
        {
            "Learned": "Ace",
            "Name": "Light Screen"
        },
        {
            "Learned": "Ace",
            "Name": "Thunder"
        },
        {
            "Learned": "Pro",
            "Name": "Agility"
        },
        {
            "Learned": "Pro",
            "Name": "Magnet Rise"
        },
        {
            "Learned": "Pro",
            "Name": "Heal Bell"
        }
    ]
}