{
    "Name": "Marshadow",
    "_id": "marshadow",
    "Moves": [
        {
            "Learned": "Master",
            "Name": "Laser Focus"
        },
        {
            "Learned": "Master",
            "Name": "Assurance"
        },
        {
            "Learned": "Master",
            "Name": "Fire Punch"
        },
        {
            "Learned": "Master",
            "Name": "Ice Punch"
        },
        {
            "Learned": "Master",
            "Name": "Thunder Punch"
        },
        {
            "Learned": "Master",
            "Name": "Drain Punch"
        },
        {
            "Learned": "Master",
            "Name": "Counter"
        },
        {
            "Learned": "Master",
            "Name": "Pursuit"
        },
        {
            "Learned": "Master",
            "Name": "Shadow Sneak"
        },
        {
            "Learned": "Master",
            "Name": "Force Palm"
        },
        {
            "Learned": "Master",
            "Name": "Feint"
        },
        {
            "Learned": "Master",
            "Name": "Rolling Kick"
        },
        {
            "Learned": "Master",
            "Name": "Copycat"
        },
        {
            "Learned": "Master",
            "Name": "Shadow Punch"
        },
        {
            "Learned": "Master",
            "Name": "Role Play"
        },
        {
            "Learned": "Master",
            "Name": "Jump Kick"
        },
        {
            "Learned": "Master",
            "Name": "Psych Up"
        },
        {
            "Learned": "Master",
            "Name": "Spectral Thief"
        },
        {
            "Learned": "Master",
            "Name": "Close Combat"
        },
        {
            "Learned": "Master",
            "Name": "Sucker Punch"
        },
        {
            "Learned": "Master",
            "Name": "Endeavor"
        },
        {
            "Learned": "Master",
            "Name": "Throat Chop"
        },
        {
            "Learned": "Master",
            "Name": "Poison Jab"
        },
        {
            "Learned": "Master",
            "Name": "Superpower"
        }
    ]
}