{
    "Name": "Shiftry",
    "_id": "shiftry",
    "Moves": [
        {
            "Learned": "Starter",
            "Name": "Feint Attack"
        },
        {
            "Learned": "Beginner",
            "Name": "Razor Leaf"
        },
        {
            "Learned": "Amateur",
            "Name": "Nasty Plot"
        },
        {
            "Learned": "Amateur",
            "Name": "Whirlwind"
        },
        {
            "Learned": "Amateur",
            "Name": "Leaf Tornado"
        },
        {
            "Learned": "Ace",
            "Name": "Hurricane"
        },
        {
            "Learned": "Ace",
            "Name": "Leaf Storm"
        },
        {
            "Learned": "Pro",
            "Name": "Seed Bomb"
        },
        {
            "Learned": "Pro",
            "Name": "Self Destruct"
        },
        {
            "Learned": "Pro",
            "Name": "Sucker Punch"
        }
    ]
}