{
    "Name": "Skarmory",
    "_id": "skarmory",
    "Moves": [
        {
            "Learned": "Starter",
            "Name": "Leer"
        },
        {
            "Learned": "Starter",
            "Name": "Peck"
        },
        {
            "Learned": "Beginner",
            "Name": "Sand Attack"
        },
        {
            "Learned": "Beginner",
            "Name": "Swift"
        },
        {
            "Learned": "Beginner",
            "Name": "Metal Claw"
        },
        {
            "Learned": "Amateur",
            "Name": "Agility"
        },
        {
            "Learned": "Amateur",
            "Name": "Fury Attack"
        },
        {
            "Learned": "Amateur",
            "Name": "Feint"
        },
        {
            "Learned": "Amateur",
            "Name": "Air Cutter"
        },
        {
            "Learned": "Amateur",
            "Name": "Spikes"
        },
        {
            "Learned": "Amateur",
            "Name": "Metal Sound"
        },
        {
            "Learned": "Amateur",
            "Name": "Steel Wing"
        },
        {
            "Learned": "Ace",
            "Name": "Autotomize"
        },
        {
            "Learned": "Ace",
            "Name": "Air Slash"
        },
        {
            "Learned": "Ace",
            "Name": "Slash"
        },
        {
            "Learned": "Ace",
            "Name": "Night Slash"
        },
        {
            "Learned": "Pro",
            "Name": "Brave Bird"
        },
        {
            "Learned": "Pro",
            "Name": "Ominous Wind"
        },
        {
            "Learned": "Pro",
            "Name": "Pursuit"
        }
    ]
}