{
    "Name": "Smeargle",
    "_id": "smeargle",
    "Moves": [
        {
            "Learned": "Starter",
            "Name": "Sketch"
        },
        {
            "Learned": "Starter",
            "Name": "Sketch"
        },
        {
            "Learned": "Beginner",
            "Name": "Sketch"
        },
        {
            "Learned": "Beginner",
            "Name": "Sketch"
        },
        {
            "Learned": "Amateur",
            "Name": "Sketch"
        },
        {
            "Learned": "Amateur",
            "Name": "Sketch"
        },
        {
            "Learned": "Ace",
            "Name": "Sketch"
        },
        {
            "Learned": "Ace",
            "Name": "Sketch"
        },
        {
            "Learned": "Pro",
            "Name": "Sketch"
        },
        {
            "Learned": "Pro",
            "Name": "Sketch"
        }
    ]
}