{
    "Name": "Tsareena",
    "_id": "tsareena",
    "Moves": [
        {
            "Learned": "Starter",
            "Name": "Splash"
        },
        {
            "Learned": "Starter",
            "Name": "Swagger"
        },
        {
            "Learned": "Beginner",
            "Name": "Rapid Spin"
        },
        {
            "Learned": "Beginner",
            "Name": "Razor Leaf"
        },
        {
            "Learned": "Beginner",
            "Name": "Sweet Scent"
        },
        {
            "Learned": "Amateur",
            "Name": "Double Slap"
        },
        {
            "Learned": "Amateur",
            "Name": "Trop Kick"
        },
        {
            "Learned": "Amateur",
            "Name": "Magical Leaf"
        },
        {
            "Learned": "Amateur",
            "Name": "Teeter Dance"
        },
        {
            "Learned": "Amateur",
            "Name": "Stomp"
        },
        {
            "Learned": "Amateur",
            "Name": "Aromatic Mist"
        },
        {
            "Learned": "Amateur",
            "Name": "Captivate"
        },
        {
            "Learned": "Ace",
            "Name": "Aromatherapy"
        },
        {
            "Learned": "Ace",
            "Name": "Leaf Storm"
        },
        {
            "Learned": "Ace",
            "Name": "High Jump Kick"
        },
        {
            "Learned": "Pro",
            "Name": "Acrobatics"
        },
        {
            "Learned": "Pro",
            "Name": "Low Sweep"
        },
        {
            "Learned": "Pro",
            "Name": "Synthesis"
        }
    ]
}