{
    "Name": "Turtonator",
    "_id": "turtonator",
    "Moves": [
        {
            "Learned": "Starter",
            "Name": "Ember"
        },
        {
            "Learned": "Starter",
            "Name": "Tackle"
        },
        {
            "Learned": "Beginner",
            "Name": "Smog"
        },
        {
            "Learned": "Beginner",
            "Name": "Protect"
        },
        {
            "Learned": "Amateur",
            "Name": "Incinerate"
        },
        {
            "Learned": "Amateur",
            "Name": "Flail"
        },
        {
            "Learned": "Amateur",
            "Name": "Endure"
        },
        {
            "Learned": "Amateur",
            "Name": "Iron Defense"
        },
        {
            "Learned": "Amateur",
            "Name": "Flamethrower"
        },
        {
            "Learned": "Amateur",
            "Name": "Body Slam"
        },
        {
            "Learned": "Amateur",
            "Name": "Shell Smash"
        },
        {
            "Learned": "Amateur",
            "Name": "Dragon Pulse"
        },
        {
            "Learned": "Ace",
            "Name": "Shell Trap"
        },
        {
            "Learned": "Ace",
            "Name": "Overheat"
        },
        {
            "Learned": "Ace",
            "Name": "Explosion"
        },
        {
            "Learned": "Pro",
            "Name": "Head Smash"
        },
        {
            "Learned": "Pro",
            "Name": "Flame Charge"
        },
        {
            "Learned": "Pro",
            "Name": "Wide Guard"
        }
    ]
}