{
    "Name": "Typhlosion",
    "_id": "typhlosion",
    "Moves": [
        {
            "Learned": "Starter",
            "Name": "Leer"
        },
        {
            "Learned": "Starter",
            "Name": "Tackle"
        },
        {
            "Learned": "Beginner",
            "Name": "Smokescreen"
        },
        {
            "Learned": "Beginner",
            "Name": "Quick Attack"
        },
        {
            "Learned": "Beginner",
            "Name": "Ember"
        },
        {
            "Learned": "Amateur",
            "Name": "Defense Curl"
        },
        {
            "Learned": "Amateur",
            "Name": "Flame Wheel"
        },
        {
            "Learned": "Amateur",
            "Name": "Flame Charge"
        },
        {
            "Learned": "Amateur",
            "Name": "Swift"
        },
        {
            "Learned": "Amateur",
            "Name": "Flamethrower"
        },
        {
            "Learned": "Amateur",
            "Name": "Lava Plume"
        },
        {
            "Learned": "Amateur",
            "Name": "Rollout"
        },
        {
            "Learned": "Amateur",
            "Name": "Gyro Ball"
        },
        {
            "Learned": "Ace",
            "Name": "Inferno"
        },
        {
            "Learned": "Ace",
            "Name": "Double-Edge"
        },
        {
            "Learned": "Ace",
            "Name": "Eruption"
        },
        {
            "Learned": "Ace",
            "Name": "Burn Up"
        },
        {
            "Learned": "Pro",
            "Name": "Blast Burn"
        },
        {
            "Learned": "Pro",
            "Name": "Extrasensory"
        },
        {
            "Learned": "Pro",
            "Name": "Thunder Punch"
        }
    ]
}