{
    "Number": 886,
    "DexID": "0886",
    "Name": "Drakloak",
    "Type1": "Dragon",
    "Type2": "Ghost",
    "BaseHP": 4,
    "Strength": 2,
    "MaxStrength": 5,
    "Dexterity": 3,
    "MaxDexterity": 6,
    "Vitality": 2,
    "MaxVitality": 4,
    "Special": 2,
    "MaxSpecial": 4,
    "Insight": 2,
    "MaxInsight": 4,
    "Ability1": "Clear Body",
    "Ability2": "Infiltrator",
    "HiddenAbility": "Cursed Body",
    "EventAbilities": "",
    "Unevolved": true,
    "RecommendedRank": "Ace",
    "GenderType": "",
    "Legendary": false,
    "Sprite": "drakloak.png",
    "GoodStarter": false,
    "_id": "Drakloak",
    "HasForm": false,
    "Learnset": "Drakloak-Learnset",
    "Abilities": "Clear Body / Infiltrator (Cursed Body)",
    "Type": "Dragon / Ghost"
}