{
    "Number": 136,
    "DexID": "0136",
    "Name": "Flareon",
    "Type1": "Fire",
    "Type2": "",
    "BaseHP": 4,
    "Strength": 3,
    "MaxStrength": 7,
    "Dexterity": 2,
    "MaxDexterity": 4,
    "Vitality": 2,
    "MaxVitality": 4,
    "Special": 3,
    "MaxSpecial": 6,
    "Insight": 3,
    "MaxInsight": 6,
    "Ability1": "Flash Fire",
    "Ability2": "",
    "HiddenAbility": "Guts",
    "EventAbilities": "",
    "Unevolved": false,
    "RecommendedRank": "Amateur",
    "GenderType": "",
    "Legendary": false,
    "Sprite": "flareon.png",
    "GoodStarter": false,
    "_id": "Flareon",
    "HasForm": false,
    "Learnset": "Flareon-Learnset",
    "Abilities": "Flash Fire (Guts)",
    "Type": "Fire"
}