{
    "Number": 122,
    "DexID": "0122G",
    "Name": "Galarian Mr. Mime",
    "Type1": "Ice",
    "Type2": "Psychic",
    "BaseHP": 4,
    "Strength": 2,
    "MaxStrength": 4,
    "Dexterity": 3,
    "MaxDexterity": 6,
    "Vitality": 2,
    "MaxVitality": 4,
    "Special": 2,
    "MaxSpecial": 5,
    "Insight": 2,
    "MaxInsight": 5,
    "Ability1": "Vital Spirit",
    "Ability2": "Screen Cleaner",
    "HiddenAbility": "Ice Body",
    "EventAbilities": "",
    "Unevolved": false,
    "RecommendedRank": "Amateur",
    "GenderType": "",
    "Legendary": false,
    "Sprite": "mr-mime-galar.png",
    "GoodStarter": false,
    "_id": "galarian-mr.-mime",
    "HasForm": false,
    "Learnset": "Galarian Mr. Mime-Learnset",
    "Abilities": "Vital Spirit / Screen Cleaner (Ice Body)",
    "Type": "Ice / Psychic",
    "DexCategory": "Barrier Pokemon",
    "Height": {
        "Deimeters": 14,
        "Meters": 1.4,
        "Feet": 4.6
    },
    "Weight": {
        "Hectograms": 568,
        "Kilograms": 56.8,
        "Pounds": 125.2
    },
    "DexDescription": "Mime Jr. that endure the harsh winter of Galar are able to create invisible walls that suddenly turn to ice, as they evolve they start creating ice floors that allow them to tap-dance, which they enjoy more than anything.",
    "Baby": false,
    "PrimaryEggGroup": "Human-Like",
    "SecondaryEggGroup": ""
}