{
    "Number": 350,
    "DexID": "0350",
    "Name": "Milotic",
    "Type1": "Water",
    "Type2": "",
    "BaseHP": 7,
    "Strength": 2,
    "MaxStrength": 4,
    "Dexterity": 2,
    "MaxDexterity": 5,
    "Vitality": 2,
    "MaxVitality": 5,
    "Special": 3,
    "MaxSpecial": 6,
    "Insight": 3,
    "MaxInsight": 6,
    "Ability1": "Marvel Scale",
    "Ability2": "Competitive",
    "HiddenAbility": "Cute Charm",
    "EventAbilities": "",
    "RecommendedRank": "Ace",
    "GenderType": "",
    "Legendary": false,
    "GoodStarter": false,
    "_id": "milotic",
    "DexCategory": "Tender Pokemon",
    "Height": {
        "Meters": 6.2,
        "Feet": 20.3
    },
    "Weight": {
        "Kilograms": 162.0,
        "Pounds": 357.1
    },
    "DexDescription": "Milotic is considered to be one of the most beautiful Pokemon in existence. It has inspired music, paintings and statues. It has the power to calm the anger and hostility of its foes.",
    "Evolutions": [
        {
            "From": "Feebas",
            "Kind": "Stat",
            "Stat": "Beauty",
            "Value": 5
        }
    ],
    "Image": "milotic.png"
}