{
    "Number": 562,
    "DexID": "0562",
    "Name": "Yamask",
    "Type1": "Ghost",
    "Type2": "",
    "BaseHP": 3,
    "Strength": 1,
    "MaxStrength": 3,
    "Dexterity": 1,
    "MaxDexterity": 3,
    "Vitality": 2,
    "MaxVitality": 5,
    "Special": 2,
    "MaxSpecial": 4,
    "Insight": 2,
    "MaxInsight": 4,
    "Ability1": "Mummy",
    "Ability2": "",
    "HiddenAbility": "",
    "EventAbilities": "",
    "Unevolved": true,
    "RecommendedRank": "Amateur",
    "GenderType": "",
    "Legendary": false,
    "Sprite": "yamask.png",
    "GoodStarter": true,
    "_id": "Yamask",
    "HasForm": false,
    "Learnset": "Yamask-Learnset",
    "Abilities": "Mummy",
    "Types": "Ghost"
}