{
    "Number": 840,
    "DexID": "0840",
    "Name": "Applin",
    "Type1": "Grass",
    "Type2": "Dragon",
    "BaseHP": 3,
    "Strength": 2,
    "MaxStrength": 4,
    "Dexterity": 2,
    "MaxDexterity": 4,
    "Vitality": 2,
    "MaxVitality": 4,
    "Special": 2,
    "MaxSpecial": 4,
    "Insight": 2,
    "MaxInsight": 4,
    "Ability1": "Ripen",
    "Ability2": "Gluttony",
    "HiddenAbility": "Bulletproof",
    "EventAbilities": "",
    "RecommendedRank": "Starter",
    "GenderType": "",
    "Legendary": false,
    "GoodStarter": true,
    "_id": "applin",
    "DexCategory": "Apple Core Pokémon",
    "Height": {
        "Meters": 0.2,
        "Feet": 0.75
    },
    "Weight": {
        "Kilograms": 0.5,
        "Pounds": 1.0
    },
    "DexDescription": "As soon as it's born, this tiny lizard Pokémon burrows into an apple to protect itself from flying Pokémon and predators. The apple serves as its food source and the flavor of it will determine its evolution.",
    "Evolutions": [
        {
            "To": "Flapple",
            "Kind": "Item",
            "Item": "Tart Apple"
        },
        {
            "To": "Appletun",
            "Kind": "Item",
            "Item": "Sweet Apple"
        },
        {
            "To": "Dipplin",
            "Kind": "Item",
            "Item": "Candy Apple"
        }
    ],
    "Image": "applin.png",
    "Moves": [
        {
            "Learned": "Starter",
            "Name": "Withdraw"
        },
        {
            "Learned": "Starter",
            "Name": "Astonish"
        },
        {
            "Learned": "Rookie",
            "Name": "Defense Curl"
        },
        {
            "Learned": "Rookie",
            "Name": "Rollout"
        },
        {
            "Learned": "Standard",
            "Name": "Recycle"
        },
        {
            "Learned": "Advanced",
            "Name": "Sucker Punch"
        }
    ]
}
