{
    "Number": 581,
    "DexID": "0581",
    "Name": "Swanna",
    "Type1": "Water",
    "Type2": "Flying",
    "BaseHP": 5,
    "Strength": 2,
    "MaxStrength": 5,
    "Dexterity": 3,
    "MaxDexterity": 6,
    "Vitality": 2,
    "MaxVitality": 5,
    "Special": 2,
    "MaxSpecial": 5,
    "Insight": 2,
    "MaxInsight": 4,
    "Ability1": "Big Pecks",
    "Ability2": "Hydration",
    "HiddenAbility": "",
    "EventAbilities": "",
    "RecommendedRank": "Advanced",
    "GenderType": "",
    "Legendary": false,
    "GoodStarter": false,
    "_id": "swanna",
    "DexCategory": "White Bird Pokémon",
    "Height": {
        "Meters": 1.3,
        "Feet": 4.3
    },
    "Weight": {
        "Kilograms": 24.0,
        "Pounds": 53.0
    },
    "DexDescription": "Swanna come out to dance at dusk. The one dancing in the middle is the leader of the flock. Despite their elegant and frail appearance, they can flap their wings strongly and fly for thousands of miles.",
    "Evolutions": [
        {
            "From": "Ducklett",
            "Kind": "Level",
            "Speed": "Medium"
        }
    ],
    "Image": "swanna.png",
    "Moves": [
        {
            "Learned": "Starter",
            "Name": "Water Gun"
        },
        {
            "Learned": "Starter",
            "Name": "Water Sport"
        },
        {
            "Learned": "Rookie",
            "Name": "Defog"
        },
        {
            "Learned": "Rookie",
            "Name": "Wing Attack"
        },
        {
            "Learned": "Standard",
            "Name": "Water Pulse"
        },
        {
            "Learned": "Standard",
            "Name": "Aerial Ace"
        },
        {
            "Learned": "Standard",
            "Name": "Bubble Beam"
        },
        {
            "Learned": "Standard",
            "Name": "Feather Dance"
        },
        {
            "Learned": "Advanced",
            "Name": "Fly"
        },
        {
            "Learned": "Advanced",
            "Name": "Mirror Move"
        },
        {
            "Learned": "Advanced",
            "Name": "Attract"
        },
        {
            "Learned": "Advanced",
            "Name": "Icy Wind"
        },
        {
            "Learned": "Advanced",
            "Name": "Aqua Ring"
        },
        {
            "Learned": "Advanced",
            "Name": "Air Slash"
        },
        {
            "Learned": "Expert",
            "Name": "Roost"
        },
        {
            "Learned": "Expert",
            "Name": "Rain Dance"
        },
        {
            "Learned": "Expert",
            "Name": "Brine"
        },
        {
            "Learned": "Expert",
            "Name": "Lucky Chant"
        },
        {
            "Learned": "Expert",
            "Name": "Tailwind"
        },
        {
            "Learned": "Expert",
            "Name": "Brave Bird"
        },
        {
            "Learned": "Expert",
            "Name": "Hurricane"
        },
        {
            "Learned": "Ace",
            "Name": "Liquidation"
        },
        {
            "Learned": "Ace",
            "Name": "Secret Power"
        },
        {
            "Learned": "Ace",
            "Name": "Mud Sport"
        }
    ]
}
